nonebot_plugin_bilibili_yuan/__init__.py
nonebot_plugin_bilibili_yuan-0.1.0.dist-info/LICENSE
nonebot_plugin_bilibili_yuan-0.1.0.dist-info/METADATA
nonebot_plugin_bilibili_yuan-0.1.0.dist-info/WHEEL
nonebot_plugin_bilibili_yuan-0.1.0.dist-info/RECORD
