Metadata-Version: 2.1
Name: nonebot-plugin-bilibili-yuan
Version: 0.1.0
Summary: 一个基于nonebot的哔哩哔哩登录插件
License: MIT
Author: mengxinyuan
Author-email: 1648576390@qq.com
Requires-Python: >=3.8,<4.0
Classifier: License :: OSI Approved :: MIT License
Classifier: Programming Language :: Python :: 3
Classifier: Programming Language :: Python :: 3.8
Classifier: Programming Language :: Python :: 3.9
Classifier: Programming Language :: Python :: 3.10
Classifier: Programming Language :: Python :: 3.11
Requires-Dist: Pillow (==9.3.0)
Requires-Dist: httpx (==0.23.0)
Requires-Dist: nonebot-adapter-onebot (==2.1.5)
Requires-Dist: nonebot2 (==2.0.0rc1)
Requires-Dist: qrcode (==7.3.1)
